test_bench_control/__init__.py
test_bench_control/camera.py
test_bench_control/motor.py
test_bench_control-0.0.3.dist-info/METADATA
test_bench_control-0.0.3.dist-info/WHEEL
test_bench_control-0.0.3.dist-info/licenses/LICENSE
test_bench_control-0.0.3.dist-info/RECORD
