Metadata-Version: 2.1
Name: test_bench_control
Version: 0.0.3
Summary: For controlling our test bench camera and motor
Author-email: David Hecht <david.lucca@web.de>
License-File: LICENSE
Classifier: License :: OSI Approved :: MIT License
Classifier: Operating System :: OS Independent
Classifier: Programming Language :: Python :: 3
Requires-Python: >=3.7
